devto/__init__.py
devto/client.py
devto/models.py
devto-0.1.3.dist-info/METADATA
devto-0.1.3.dist-info/WHEEL
devto-0.1.3.dist-info/top_level.txt
devto-0.1.3.dist-info/RECORD
