Metadata-Version: 2.1
Name: devto
Version: 0.1.3
Summary: Modern Dev.To API client built with aiohttp and pydantic
Requires-Python: >=3.12
Requires-Dist: aiohttp>=3.11.11
Requires-Dist: aiohttp-client-cache>=0.12.4
Requires-Dist: aiosqlite>=0.20.0
Requires-Dist: loguru>=0.7.3
Requires-Dist: pydantic>=2.10.4
